pmvalsampsize/__init__.py
pmvalsampsize/pmvalsampsize.py
pmvalsampsize-0.2.1.dist-info/LICENSE
pmvalsampsize-0.2.1.dist-info/METADATA
pmvalsampsize-0.2.1.dist-info/WHEEL
pmvalsampsize-0.2.1.dist-info/RECORD
